pdbpose/__init__.py
pdbpose/__main__.py
pdbpose/cli.py
pdbpose/pdbe.py
pdbpose-0.1.0a0.dist-info/LICENSE
pdbpose-0.1.0a0.dist-info/METADATA
pdbpose-0.1.0a0.dist-info/WHEEL
pdbpose-0.1.0a0.dist-info/entry_points.txt
pdbpose-0.1.0a0.dist-info/top_level.txt
pdbpose-0.1.0a0.dist-info/RECORD
