Metadata-Version: 2.1
Name: pdbpose
Version: 0.1.0a0
Summary: Superpose PDB chains and the interactions they make
Home-page: https://github.com/paulsbond/pdbpose
Author: Paul Bond
Author-email: paul.bond@york.ac.uk
License: MIT
Requires-Python: >=3.6
License-File: LICENSE
Requires-Dist: requests
